LICENSE.txt
MANIFEST.in
README.rst
VERSION.txt
setup.cfg
setup.py
docs/source/changelog.rst
twapi_users/__init__.py
twapi_users/testing.py
twapi_users.egg-info/PKG-INFO
twapi_users.egg-info/SOURCES.txt
twapi_users.egg-info/dependency_links.txt
twapi_users.egg-info/requires.txt
twapi_users.egg-info/top_level.txt